[
  {
    "id": "Harbor Freight Store 150",
    "image": "https://newsroom.harborfreight.com/wp-content/uploads/2024/08/Valparaiso-IN-New-Store-.png?w=820",
    "name": "Harbor Freight Tools",
    "address": "2506 W Parmer Ln Ste 110",
    "city": "Austin",
    "state": "TX",
    "latitude": 30.418,
    "longitude": -97.7075
  },
  {
    "id": "Harbor Freight Store 151",
    "image": "https://newsroom.harborfreight.com/wp-content/uploads/2024/08/Valparaiso-IN-New-Store-.png?w=820",
    "name": "Harbor Freight Tools",
    "address": "4001 S Lamar Blvd Ste 3",
    "city": "Austin",
    "state": "TX",
    "latitude": 30.231,
    "longitude": -97.7879
  },
  {
    "id": "Harbor Freight Store 152",
    "image": "https://newsroom.harborfreight.com/wp-content/uploads/2024/08/Valparaiso-IN-New-Store-.png?w=820",
    "name": "Harbor Freight Tools",
    "address": "900 N Austin Ave Ste 109",
    "city": "Georgetown",
    "state": "TX",
    "latitude": 30.6437,
    "longitude": -97.6772
  },
  {
    "id": "Harbor Freight Store 153",
    "image": "https://newsroom.harborfreight.com/wp-content/uploads/2024/08/Valparaiso-IN-New-Store-.png?w=820",
    "name": "Harbor Freight Tools",
    "address": "5807 SW 45th Ave Ste 450",
    "city": "Amarillo",
    "state": "TX",
    "latitude": 35.1604,
    "longitude": -101.9033
  },
  {
    "id": "Harbor Freight Store 154",
    "image": "https://newsroom.harborfreight.com/wp-content/uploads/2024/08/Valparaiso-IN-New-Store-.png?w=820",
    "name": "Harbor Freight Tools",
    "address": "1616 I-40 E",
    "city": "Amarillo",
    "state": "TX",
    "latitude": 35.2072,
    "longitude": -101.812
  },
  {
    "id": "Harbor Freight Store 155",
    "image": "https://newsroom.harborfreight.com/wp-content/uploads/2024/08/Valparaiso-IN-New-Store-.png?w=820",
    "name": "Harbor Freight Tools",
    "address": "17700 San Pedro Ave",
    "city": "San Antonio",
    "state": "TX",
    "latitude": 29.6046,
    "longitude": -98.478
  },
  {
    "id": "Harbor Freight Store 156",
    "image": "https://newsroom.harborfreight.com/wp-content/uploads/2024/08/Valparaiso-IN-New-Store-.png?w=820",
    "name": "Harbor Freight Tools",
    "address": "7555 NW Loop 410 Ste 108",
    "city": "San Antonio",
    "state": "TX",
    "latitude": 29.5121,
    "longitude": -98.6033
  },
  {
    "id": "Harbor Freight Store 157",
    "image": "https://newsroom.harborfreight.com/wp-content/uploads/2024/08/Valparaiso-IN-New-Store-.png?w=820",
    "name": "Harbor Freight Tools",
    "address": "1803 Vance Jackson Rd",
    "city": "San Antonio",
    "state": "TX",
    "latitude": 29.4904,
    "longitude": -98.5137
  },
  {
    "id": "Harbor Freight Store 158",
    "image": "https://newsroom.harborfreight.com/wp-content/uploads/2024/08/Valparaiso-IN-New-Store-.png?w=820",
    "name": "Harbor Freight Tools",
    "address": "5464 Walzem Rd",
    "city": "San Antonio",
    "state": "TX",
    "latitude": 29.5089,
    "longitude": -98.3602
  },
  {
    "id": "Harbor Freight Store 159",
    "image": "https://newsroom.harborfreight.com/wp-content/uploads/2024/08/Valparaiso-IN-New-Store-.png?w=820",
    "name": "Harbor Freight Tools",
    "address": "185 SW Military Dr",
    "city": "San Antonio",
    "state": "TX",
    "latitude": 29.3549,
    "longitude": -98.5035
  },
  {
    "id": "Harbor Freight Store 171",
    "image": "https://newsroom.harborfreight.com/wp-content/uploads/2024/08/Valparaiso-IN-New-Store-.png?w=820",
    "name": "Harbor Freight Tools",
    "address": "1864 S WW White Rd",
    "city": "San Antonio",
    "state": "TX",
    "latitude": 29.4026,
    "longitude": -98.4053
  },
  {
    "id": "Harbor Freight Store 172",
    "image": "https://newsroom.harborfreight.com/wp-content/uploads/2024/08/Valparaiso-IN-New-Store-.png?w=820",
    "name": "Harbor Freight Tools",
    "address": "1000 Southmore Ave Ste 180",
    "city": "Pasadena",
    "state": "TX",
    "latitude": 29.6927,
    "longitude": -95.2172
  },
  {
    "id": "Harbor Freight Store 173",
    "image": "https://newsroom.harborfreight.com/wp-content/uploads/2024/08/Valparaiso-IN-New-Store-.png?w=820",
    "name": "Harbor Freight Tools",
    "address": "6800 Spencer Hwy",
    "city": "Pasadena",
    "state": "TX",
    "latitude": 29.6657,
    "longitude": -95.1595
  },
  {
    "id": "Harbor Freight Store 174",
    "image": "https://newsroom.harborfreight.com/wp-content/uploads/2024/08/Valparaiso-IN-New-Store-.png?w=820",
    "name": "Harbor Freight Tools",
    "address": "900 W Arbrook Blvd",
    "city": "Arlington",
    "state": "TX",
    "latitude": 32.6602,
    "longitude": -97.1174
  },
  {
    "id": "Harbor Freight Store 175",
    "image": "https://newsroom.harborfreight.com/wp-content/uploads/2024/08/Valparaiso-IN-New-Store-.png?w=820",
    "name": "Harbor Freight Tools",
    "address": "2000 W University Dr",
    "city": "Denton",
    "state": "TX",
    "latitude": 33.228,
    "longitude": -97.157
  },
  {
    "id": "Harbor Freight Store 176",
    "image": "https://newsroom.harborfreight.com/wp-content/uploads/2024/08/Valparaiso-IN-New-Store-.png?w=820",
    "name": "Harbor Freight Tools",
    "address": "1125 N Central Expy",
    "city": "Plano",
    "state": "TX",
    "latitude": 33.0225,
    "longitude": -96.6993
  },
  {
    "id": "Harbor Freight Store 177",
    "image": "https://newsroom.harborfreight.com/wp-content/uploads/2024/08/Valparaiso-IN-New-Store-.png?w=820",
    "name": "Harbor Freight Tools",
    "address": "2530 Gus Thomasson Rd",
    "city": "Dallas",
    "state": "TX",
    "latitude": 32.8095,
    "longitude": -96.6517
  },
  {
    "id": "Harbor Freight Store 178",
    "image": "https://newsroom.harborfreight.com/wp-content/uploads/2024/08/Valparaiso-IN-New-Store-.png?w=820",
    "name": "Harbor Freight Tools",
    "address": "2001 S Shiloh Rd",
    "city": "Garland",
    "state": "TX",
    "latitude": 32.8905,
    "longitude": -96.6498
  },
  {
    "id": "Harbor Freight Store 179",
    "image": "https://newsroom.harborfreight.com/wp-content/uploads/2024/08/Valparaiso-IN-New-Store-.png?w=820",
    "name": "Harbor Freight Tools",
    "address": "3175 N George Bush Hwy",
    "city": "Richardson",
    "state": "TX",
    "latitude": 32.981,
    "longitude": -96.6825
  },
  {
    "id": "Harbor Freight Store 180",
    "image": "https://newsroom.harborfreight.com/wp-content/uploads/2024/08/Valparaiso-IN-New-Store-.png?w=820",
    "name": "Harbor Freight Tools",
    "address": "1235 S Main St",
    "city": "Fort Worth",
    "state": "TX",
    "latitude": 32.7295,
    "longitude": -97.3213
  },
  {
    "id": "Harbor Freight Store 181",
    "image": "https://newsroom.harborfreight.com/wp-content/uploads/2024/08/Valparaiso-IN-New-Store-.png?w=820",
    "name": "Harbor Freight Tools",
    "address": "7955 Grapevine Hwy",
    "city": "North Richland Hills",
    "state": "TX",
    "latitude": 32.8487,
    "longitude": -97.2185
  },
  {
    "id": "Harbor Freight Store 182",
    "image": "https://newsroom.harborfreight.com/wp-content/uploads/2024/08/Valparaiso-IN-New-Store-.png?w=820",
    "name": "Harbor Freight Tools",
    "address": "1120 W Pioneer Pkwy",
    "city": "Grand Prairie",
    "state": "TX",
    "latitude": 32.7078,
    "longitude": -97.0205
  },
  {
    "id": "Harbor Freight Store 183",
    "image": "https://newsroom.harborfreight.com/wp-content/uploads/2024/08/Valparaiso-IN-New-Store-.png?w=820",
    "name": "Harbor Freight Tools",
    "address": "3601 Spencer Hwy",
    "city": "Pasadena",
    "state": "TX",
    "latitude": 29.6641,
    "longitude": -95.1873
  },
  {
    "id": "Harbor Freight Store 184",
    "image": "https://newsroom.harborfreight.com/wp-content/uploads/2024/08/Valparaiso-IN-New-Store-.png?w=820",
    "name": "Harbor Freight Tools",
    "address": "3450 Palmer Hwy",
    "city": "Texas City",
    "state": "TX",
    "latitude": 29.391,
    "longitude": -94.9481
  },
  {
    "id": "Harbor Freight Store 185",
    "image": "https://newsroom.harborfreight.com/wp-content/uploads/2024/08/Valparaiso-IN-New-Store-.png?w=820",
    "name": "Harbor Freight Tools",
    "address": "2400 E Expressway 83",
    "city": "Mission",
    "state": "TX",
    "latitude": 26.2057,
    "longitude": -98.3024
  },
  {
    "id": "Harbor Freight Store 186",
    "image": "https://newsroom.harborfreight.com/wp-content/uploads/2024/08/Valparaiso-IN-New-Store-.png?w=820",
    "name": "Harbor Freight Tools",
    "address": "500 N Jackson Rd",
    "city": "Pharr",
    "state": "TX",
    "latitude": 26.2095,
    "longitude": -98.1831
  },
  {
    "id": "Harbor Freight Store 187",
    "image": "https://newsroom.harborfreight.com/wp-content/uploads/2024/08/Valparaiso-IN-New-Store-.png?w=820",
    "name": "Harbor Freight Tools",
    "address": "3138 Andrews Hwy",
    "city": "Odessa",
    "state": "TX",
    "latitude": 31.8716,
    "longitude": -102.3676
  },
  {
    "id": "Harbor Freight Store 188",
    "image": "https://newsroom.harborfreight.com/wp-content/uploads/2024/08/Valparaiso-IN-New-Store-.png?w=820",
    "name": "Harbor Freight Tools",
    "address": "6601 19th St",
    "city": "Lubbock",
    "state": "TX",
    "latitude": 33.5779,
    "longitude": -101.96
  },
  {
    "id": "Harbor Freight Store 189",
    "image": "https://newsroom.harborfreight.com/wp-content/uploads/2024/08/Valparaiso-IN-New-Store-.png?w=820",
    "name": "Harbor Freight Tools",
    "address": "3110 Franklin Ave",
    "city": "Waco",
    "state": "TX",
    "latitude": 31.5301,
    "longitude": -97.164
  },
  {
    "id": "Harbor Freight Store 190",
    "image": "https://newsroom.harborfreight.com/wp-content/uploads/2024/08/Valparaiso-IN-New-Store-.png?w=820",
    "name": "Harbor Freight Tools",
    "address": "2015 S Beckham Ave",
    "city": "Tyler",
    "state": "TX",
    "latitude": 32.3272,
    "longitude": -95.3007
  }
]
